__init__.py
fold_resize_images.py
fold_resize_images-1.0.9.dist-info/LICENSE
fold_resize_images-1.0.9.dist-info/METADATA
fold_resize_images-1.0.9.dist-info/WHEEL
fold_resize_images-1.0.9.dist-info/entry_points.txt
fold_resize_images-1.0.9.dist-info/top_level.txt
fold_resize_images-1.0.9.dist-info/RECORD
