Metadata-Version: 2.1
Name: fold_resize_images
Version: 1.0.9
Summary: A simple tool to resize images in a directory.
Author-email: Tadiello Sebastien <sebastientadiello@gmail.com>
Project-URL: Homepage, https://github.com/sebDtSci/fold_resize_images
Classifier: Programming Language :: Python :: 3
Classifier: License :: OSI Approved :: MIT License
Classifier: Operating System :: OS Independent
Requires-Python: >=3.8
License-File: LICENSE
Requires-Dist: Pillow
